Metadata-Version: 1.0
Name: django-debug-toolbar-template-flamegraph
Version: 0.2.2
Summary: Template flamegraphs for Django Debug Toolbar
Home-page: http://github.com/inglesp/django-debug-toolbar-template-flamegraph
Author: Peter Inglesby
Author-email: peter.inglesby@gmail.com
License: License :: OSI Approved :: MIT License
Platform: UNKNOWN
